numpy-stubs/__init__.pyi
numtype-0.0.0.0.dist-info/METADATA
numtype-0.0.0.0.dist-info/WHEEL
numtype-0.0.0.0.dist-info/licenses/LICENSE
numtype-0.0.0.0.dist-info/RECORD
